maven <?xml version="1.0" encoding="UTF-8"?>
<settings xsi:schemaLocation="http://maven.apache.org/SETTINGS/1.1.0 http://maven.apache.org/xsd/settings-1.1.0.xsd" xmlns="http://maven.apache.org/SETTINGS/1.1.0"
    xmlns:xsi="http://www.w3.org/2001/XMLSchema-instance">
  <profiles>
    <profile>
      <repositories>
        <repository>
          <id>central</id>
          <name>maven-central</name>
          <url>https://repo1.maven.org/maven2/</url>
          <releases>
            <enabled>true</enabled>
          </releases>
          <snapshots>
            <enabled>false</enabled>
          </snapshots>
        </repository>
        <repository>
          <id>ext</id>
          <name>ext-release</name>
          <url>https://idos-nexus.awscloud.cms.local/repository/ext-release-local/</url>
          <releases>
            <enabled>true</enabled>
          </releases>
          <snapshots>
            <enabled>false</enabled>
          </snapshots>
        </repository>
        <repository>
          <id>releases</id>
          <name>libs-release</name>
          <url>https://idos-nexus.awscloud.cms.local/repository/libs-release-local/</url>
          <releases>
            <enabled>true</enabled>
          </releases>
          <snapshots>
            <enabled>false</enabled>
          </snapshots>
        </repository>
        <repository>
          <id>snapshots</id>
          <name>libs-snapshot</name>
          <url>https://idos-nexus.awscloud.cms.local/repository/libs-snapshot-local/</url>
          <releases>
            <enabled>false</enabled>
          </releases>
          <snapshots>
            <enabled>true</enabled>
          </snapshots>
        </repository>
      </repositories>
      <pluginRepositories>
        <pluginRepository>
          <id>central</id>
          <name>plugins-central</name>
          <url>https://repo1.maven.org/maven2/</url>
          <releases>
            <enabled>true</enabled>
          </releases>
          <snapshots>
            <enabled>false</enabled>
          </snapshots>
        </pluginRepository>
        <pluginRepository>
          <id>releases</id>
          <name>plugins-release</name>
          <url>https://idos-nexus.awscloud.cms.local/repository/plugins-release-local/</url>
          <releases>
            <enabled>true</enabled>
          </releases>
          <snapshots>
            <enabled>false</enabled>
          </snapshots>
        </pluginRepository>
        <pluginRepository>
          <id>snapshots</id>
          <name>plugins-snapshot</name>
          <url>https://idos-nexus.awscloud.cms.local/repository/plugins-snapshot-local/</url>
          <releases>
            <enabled>false</enabled>
          </releases>
          <snapshots>
            <enabled>true</enabled>
          </snapshots>
        </pluginRepository>
      </pluginRepositories>
      <id>artifactory</id>
    </profile>
  </profiles>
  <activeProfiles>
    <activeProfile>artifactory</activeProfile>
  </activeProfiles>
</settings>